{
  "TranslationProperties": {
    "Name": "Gravestone",
    "Description": "Gravestone"
  },
  "PlayerAnimationsId": "Block",
  "Categories": [
    "Furniture.Containers"
  ],
  "Icon": "Icons/ItemsGenerated/Gravestone.png",
  "BlockType": {
    "Material": "Solid",
    "Opacity": "Transparent",
    "DrawType": "Model",
    "State": {
      "Id": "Gravestone",
      "Capacity": 1
    },
    "VariantRotation": "NESW",
    "CustomModel": "Blocks/Gravestone/Gravestone.blockymodel",
    "CustomModelTexture": [
      {
        "Texture": "Blocks/Gravestone/Gravestone.png",
        "Weight": 1
      }
    ],
    "Interactions": {
      "Primary": "Break_Container",
      "Use": "Open_Container"
    },
    "CubeShadingMode": "Fullbright",
    "Gathering": {
      "Soft": {}
    }
  },
  "IconProperties": {
    "Scale": 0.55,
    "Rotation": [
      22.5,
      45,
      22.5
    ],
    "Translation": [
      0,
      -15
    ]
  }
}
